moodleapi/__init__.py
moodleapi/decorator.py
moodleapi/moodleapi.py
moodleapi/utilurl.py
moodleapi-0.0.4.dist-info/METADATA
moodleapi-0.0.4.dist-info/WHEEL
moodleapi-0.0.4.dist-info/top_level.txt
moodleapi-0.0.4.dist-info/RECORD
