Metadata-Version: 2.1
Name: moodleapi
Version: 0.0.4
Summary: moodle api
Home-page: UNKNOWN
Author: Isaac Bruno Quiroga
License: UNKNOWN
Platform: UNKNOWN
Requires-Python: >=3.6
